demograpyx/__init__.py
demograpyx/clients.py
demograpyx/exceptions.py
demograpyx/objects.py
demograpyx-1.0.0.dist-info/METADATA
demograpyx-1.0.0.dist-info/WHEEL
demograpyx-1.0.0.dist-info/RECORD
