Metadata-Version: 2.3
Name: demograpyx
Version: 1.0.0
Summary: An asynchronous set of bindings for the three Demografix APIs - Genderize, Agify and Nationalize
License: MIT
Author: cobaltgit
Author-email: cobaltsecuremail312@proton.me
Requires-Python: >=3.10
Classifier: License :: OSI Approved :: MIT License
Classifier: Programming Language :: Python :: 3
Classifier: Programming Language :: Python :: 3.10
Classifier: Programming Language :: Python :: 3.11
Classifier: Programming Language :: Python :: 3.12
Classifier: Programming Language :: Python :: 3.13
Requires-Dist: aiohttp (>=3.11.14,<4.0.0)
